hashin.py
hashin-1.0.5.dist-info/licenses/LICENSE
hashin-1.0.5.dist-info/METADATA
hashin-1.0.5.dist-info/WHEEL
hashin-1.0.5.dist-info/entry_points.txt
hashin-1.0.5.dist-info/top_level.txt
hashin-1.0.5.dist-info/RECORD
